streamcontroller_plugin_tools/BackendBase.py
streamcontroller_plugin_tools/__init__.py
streamcontroller_plugin_tools/installation_helpers.py
streamcontroller_plugin_tools-2.0.0.dist-info/METADATA
streamcontroller_plugin_tools-2.0.0.dist-info/WHEEL
streamcontroller_plugin_tools-2.0.0.dist-info/top_level.txt
streamcontroller_plugin_tools-2.0.0.dist-info/RECORD
